pydriosm/__init__.py
pydriosm/_updater.py
pydriosm/downloader.py
pydriosm/errors.py
pydriosm/ios.py
pydriosm/reader.py
pydriosm/utils.py
pydriosm/data/bbbike_cities.pkl
pydriosm/data/bbbike_cities_coordinates.pkl
pydriosm/data/bbbike_downloads_catalogue.pkl
pydriosm/data/bbbike_index_of_subregions.pkl
pydriosm/data/bbbike_subregion_names.pkl
pydriosm/data/geofabrik_continent_tables.pkl
pydriosm/data/geofabrik_downloads_catalogue.pkl
pydriosm/data/geofabrik_index_of_subregions.pkl
pydriosm/data/geofabrik_region-subregion_tier.pkl
pydriosm/data/geofabrik_subregion_names.pkl
pydriosm/data/metadata.json
pydriosm-2.2.0.dist-info/LICENSE
pydriosm-2.2.0.dist-info/METADATA
pydriosm-2.2.0.dist-info/WHEEL
pydriosm-2.2.0.dist-info/top_level.txt
pydriosm-2.2.0.dist-info/RECORD
