Metadata-Version: 2.1
Name: pydriosm
Version: 2.2.0
Summary: An open-source tool for downloading, reading and PostgreSQL-based I/O of OpenStreetMap data.
Home-page: https://github.com/mikeqfu/pydriosm
Author: Qian Fu
Author-email: q.fu@bham.ac.uk
License: GPLv3+
Project-URL: Documentation, https://pydriosm.readthedocs.io/en/2.2.0/
Project-URL: Source, https://github.com/mikeqfu/pydriosm
Project-URL: Issue Tracker, https://github.com/mikeqfu/pydriosm/issues
Keywords: Python,OpenStreetMap,OSM,Geofabrik,BBBike,Protocolbuffer Binary Format,PBF,Shapefile,PostgreSQL
Platform: nt
Platform: posix
Classifier: Intended Audience :: Developers
Classifier: Intended Audience :: Education
Classifier: Intended Audience :: End Users/Desktop
Classifier: Intended Audience :: Information Technology
Classifier: Intended Audience :: Science/Research
Classifier: Topic :: Education
Classifier: Topic :: Scientific/Engineering
Classifier: Topic :: Software Development
Classifier: Topic :: Utilities
Classifier: License :: OSI Approved :: GNU General Public License v3 or later (GPLv3+)
Classifier: Programming Language :: Python :: 3
Classifier: Operating System :: Microsoft :: Windows
Classifier: Operating System :: POSIX :: Linux
Requires-Python: >=3.9
License-File: LICENSE
Requires-Dist: pyhelpers (>=1.5.1)
Requires-Dist: pyrcs (>=0.3.6)
Requires-Dist: pyshp
